graylog_archiver
