Metadata-Version: 1.0
Name: graylog-archiver
Version: 0.1.3
Summary: Archives graylog indices
Home-page: https://github.com/NDrive/graylog-archiver
Author: André Freitas
Author-email: andre.freitas@ndrive.com
License: MIT
Platform: UNKNOWN
